MANIFEST.in
README.md
license.txt
setup.py
python_grains/__init__.py
python_grains/version.py
python_grains.egg-info/PKG-INFO
python_grains.egg-info/SOURCES.txt
python_grains.egg-info/dependency_links.txt
python_grains.egg-info/requires.txt
python_grains.egg-info/top_level.txt
python_grains/aliassing/__init__.py
python_grains/aliassing/aliassing.py
python_grains/dynamic_settings/__init__.py
python_grains/dynamic_settings/dynamic_settings.py
python_grains/dynamic_settings/lua.py
python_grains/experiments/__init__.py
python_grains/experiments/experiments.py
python_grains/locks/__init__.py
python_grains/locks/locks.py
python_grains/profiles/__init__.py
python_grains/profiles/audiences.py
python_grains/profiles/exceptions.py
python_grains/profiles/getter.py
python_grains/profiles/lua.py
python_grains/profiles/profile_properties.py
python_grains/profiles/profiles.py
python_grains/profiles/stitches.py
python_grains/profiles/stitching.py
python_grains/queues/__init__.py
python_grains/queues/lua.py
python_grains/queues/queues.py
python_grains/splunk/__init__.py
python_grains/splunk/splunk.py
python_grains/utils/__init__.py
python_grains/utils/utils.py