Metadata-Version: 2.1
Name: python-grains
Version: 0.9.4
Summary: Grains of Python
Home-page: UNKNOWN
Author: Jacob Noordmans
Author-email: jacob@graindataconsultants.com
License: MIT
Keywords: Grain,Python
Platform: UNKNOWN
License-File: license.txt
